woops/__init__.py
woops/frame.py
woops/frame_collection.py
woops/inspector.py
woops-0.2.0.dist-info/LICENSE
woops-0.2.0.dist-info/WHEEL
woops-0.2.0.dist-info/METADATA
woops-0.2.0.dist-info/RECORD
